kvcd/__init__.py
kvcd/config.py
kvcd/main.py
kvcd/utils.py
kvcd/vmware/__init__.py
kvcd/vmware/vcloud_helper.py
kvcd/vmware/vcloud_vapp.py
kvcd-0.1.0.dist-info/AUTHORS.md
kvcd-0.1.0.dist-info/LICENSE
kvcd-0.1.0.dist-info/METADATA
kvcd-0.1.0.dist-info/WHEEL
kvcd-0.1.0.dist-info/top_level.txt
kvcd-0.1.0.dist-info/RECORD
