Metadata-Version: 2.1
Name: kvcd
Version: 0.1.0
Summary: A python based proof of concept of an operator to manage VMware Cloud Director ressources
Home-page: https://github.com/lrivallain/kvcd
Author: Ludovic Rivallain
License: MIT license
Keywords: kvcd
Platform: UNKNOWN
Classifier: Development Status :: 2 - Pre-Alpha
Classifier: Intended Audience :: Developers
Classifier: License :: OSI Approved :: MIT License
Classifier: Natural Language :: English
Classifier: Programming Language :: Python :: 3.6
Classifier: Programming Language :: Python :: 3.7
Classifier: Programming Language :: Python :: 3.8
Classifier: Programming Language :: Python :: 3.9
Requires-Python: >=3.6
Requires-Dist: pyvcloud
Requires-Dist: kopf
Requires-Dist: kubernetes
Requires-Dist: PyYAML
Requires-Dist: environ-config
Requires-Dist: python-dotenv
